pklshop/__init__.py
pklshop/_modidx.py
pklshop/connect.py
pklshop/data.py
pklshop/game.py
pklshop/index.py
pklshop/match.py
pklshop/name.py
pklshop/player.py
pklshop/rally.py
pklshop/stats.py
pklshop/team.py
pklshop/datasets/game.csv
pklshop/datasets/match.csv
pklshop/datasets/player.csv
pklshop/datasets/rally.csv
pklshop/datasets/shot.csv
pklshop/datasets/shot_type_ref.csv
pklshop/datasets/team.csv
pklshop/datasets/tournament.csv
pklshop-0.0.4.dist-info/LICENSE
pklshop-0.0.4.dist-info/METADATA
pklshop-0.0.4.dist-info/WHEEL
pklshop-0.0.4.dist-info/entry_points.txt
pklshop-0.0.4.dist-info/top_level.txt
pklshop-0.0.4.dist-info/RECORD
