Metadata-Version: 2.1
Name: pklshop
Version: 0.0.4
Summary: A library for accessing and analyzing Pickleball data from pklmart
Home-page: https://github.com/NolanSmyth/pklshop
Author: Nolan Smyth
Author-email: nolanwsmyth@gmail.com
License: Apache Software License 2.0
Keywords: nbdev jupyter notebook python
Classifier: Development Status :: 4 - Beta
Classifier: Intended Audience :: Developers
Classifier: Natural Language :: English
Classifier: Programming Language :: Python :: 3.7
Classifier: Programming Language :: Python :: 3.8
Classifier: Programming Language :: Python :: 3.9
Classifier: Programming Language :: Python :: 3.10
Classifier: License :: OSI Approved :: Apache Software License
Requires-Python: >=3.7
License-File: LICENSE
Requires-Dist: fastcore
Requires-Dist: pandas
Requires-Dist: psycopg2
Requires-Dist: seaborn
Provides-Extra: dev
